data_types/pending.py
handlers/response.py
nundb.py
test_nundb.py
nun_db_py-0.1.0.dist-info/METADATA
nun_db_py-0.1.0.dist-info/WHEEL
nun_db_py-0.1.0.dist-info/RECORD
