Metadata-Version: 2.1
Name: nun-db-py
Version: 0.1.0
Summary: A fan-made Python client for interacting with NunDB, a NoSQL database that supports real-time data synchronization and flexible data manipulation. This library allows you to connect to a NunDB instance, create databases, set and get values, watch data in real-time, and manage users and permissions.
Home-page: https://github.com/eewnshit/nun-db-py
License: MIT
Keywords: nun-db,client,database,real-time,python
Author: Alex
Author-email: eewnshit@gmail.com
Requires-Python: >=3.10,<4.0
Classifier: License :: OSI Approved :: MIT License
Classifier: Operating System :: OS Independent
Classifier: Programming Language :: Python :: 3
Classifier: Programming Language :: Python :: 3.10
Classifier: Programming Language :: Python :: 3.11
Classifier: Programming Language :: Python :: 3.12
Classifier: Programming Language :: Python :: 3.13
Requires-Dist: pytest (>=8.3.4,<9.0.0)
Requires-Dist: pytest-asyncio (>=0.25.0,<0.26.0)
Requires-Dist: websockets (>=14.1,<15.0)
Project-URL: Repository, https://github.com/eewnshit/nun-db-py
